rics/__init__.py
rics/__main__.py
rics/_cli_repos.py
rics/_internal_support/__init__.py
rics/_internal_support/_local_or_remote.py
rics/_internal_support/changelog/__init__.py
rics/_internal_support/changelog/_patch_notes.py
rics/_internal_support/changelog/_split_changelog.py
rics/_internal_support/changelog/_write_changelog.py
rics/_internal_support/make_toc_tree_titles_shorter.py
rics/_internal_support/myst_parser_markdown_doc_refs.py
rics/_just_the_way_i_like_it.py
rics/action_level.py
rics/cli.py
rics/click/__init__.py
rics/click/_alias_command_group.py
rics/click/_logging.py
rics/click/_util.py
rics/collections/__init__.py
rics/collections/dicts.py
rics/collections/misc.py
rics/env/__init__.py
rics/env/interpolation/__init__.py
rics/env/interpolation/_file_utils.py
rics/env/interpolation/_variable.py
rics/env/read/__init__.py
rics/env/read/_base.py
rics/env/read/_bool.py
rics/env/read/_enum.py
rics/env/read/_numeric.py
rics/env/read/_str.py
rics/envinterp/__init__.py
rics/jupyter/__init__.py
rics/jupyter/_kernel_helper.py
rics/jupyter/_kernel_spec.py
rics/jupyter/_print_paths.py
rics/jupyter/_venv_helper.py
rics/jupyter/cli.py
rics/logs.py
rics/misc.py
rics/paths.py
rics/performance/__init__.py
rics/performance/_format_perf_counter.py
rics/performance/_multi_case_timer.py
rics/performance/_plot/__init__.py
rics/performance/_plot/_params.py
rics/performance/_plot/_plot.py
rics/performance/_plot/_postprocessors.py
rics/performance/_util.py
rics/performance/_wrapper.py
rics/performance/cli.py
rics/performance/plot_types.py
rics/performance/templates/candidates.py.txt
rics/performance/templates/test_data.py.txt
rics/performance/types.py
rics/plotting.py
rics/py.typed
rics/strings.py
rics/types.py
rics-6.1.1.dist-info/METADATA
rics-6.1.1.dist-info/WHEEL
rics-6.1.1.dist-info/entry_points.txt
rics-6.1.1.dist-info/licenses/LICENSE.md
rics-6.1.1.dist-info/RECORD
