Metadata-Version: 2.4
Name: rics
Version: 6.1.1
Summary: My personal Python toolbox.
License: MIT
License-File: LICENSE.md
Keywords: rics
Author: Richard Sundqvist
Author-email: richard.sundqvist@live.se
Requires-Python: >=3.11
Classifier: Development Status :: 5 - Production/Stable
Classifier: Intended Audience :: Developers
Classifier: Intended Audience :: Science/Research
Classifier: Operating System :: POSIX :: Linux
Classifier: Operating System :: MacOS
Classifier: Operating System :: Microsoft :: Windows
Classifier: License :: OSI Approved :: MIT License
Classifier: Natural Language :: English
Classifier: Typing :: Typed
Classifier: Programming Language :: Python :: 3
Classifier: Programming Language :: Python :: 3 :: Only
Classifier: Programming Language :: Python :: 3.11
Classifier: Programming Language :: Python :: 3.12
Classifier: Programming Language :: Python :: 3.13
Classifier: Programming Language :: Python :: 3.14
Provides-Extra: cli
Provides-Extra: plotting
Requires-Dist: click (>=8.1.0) ; extra == "cli"
Requires-Dist: ipykernel (>=6.29.3) ; extra == "cli"
Requires-Dist: matplotlib ; extra == "plotting"
Requires-Dist: pandas (>=2.0.3) ; extra == "cli"
Requires-Dist: requests (>=2.30.0) ; extra == "cli"
Requires-Dist: seaborn ; extra == "plotting"
Project-URL: Bug Tracker, https://github.com/rsundqvist/rics/issues
Project-URL: Changelog, https://github.com/rsundqvist/rics/blob/master/CHANGELOG.md
Project-URL: Documentation, https://rics
Project-URL: Homepage, https://github.com/rsundqvist/rics
Project-URL: Repository, https://github.com/rsundqvist/rics
